dockertown/__init__.py
dockertown/client_config.py
dockertown/command_line_entrypoint.py
dockertown/docker_client.py
dockertown/download_binaries.py
dockertown/exceptions.py
dockertown/py.typed
dockertown/test_utils.py
dockertown/utils.py
dockertown/components/__init__.py
dockertown/components/buildx/__init__.py
dockertown/components/buildx/cli_wrapper.py
dockertown/components/buildx/models.py
dockertown/components/buildx/imagetools/__init__.py
dockertown/components/buildx/imagetools/cli_wrapper.py
dockertown/components/buildx/imagetools/models.py
dockertown/components/compose/__init__.py
dockertown/components/compose/cli_wrapper.py
dockertown/components/compose/models.py
dockertown/components/config/__init__.py
dockertown/components/config/cli_wrapper.py
dockertown/components/config/models.py
dockertown/components/container/__init__.py
dockertown/components/container/cli_wrapper.py
dockertown/components/container/models.py
dockertown/components/context/__init__.py
dockertown/components/context/cli_wrapper.py
dockertown/components/context/models.py
dockertown/components/image/__init__.py
dockertown/components/image/cli_wrapper.py
dockertown/components/image/models.py
dockertown/components/manifest/__init__.py
dockertown/components/manifest/cli_wrapper.py
dockertown/components/manifest/models.py
dockertown/components/network/__init__.py
dockertown/components/network/cli_wrapper.py
dockertown/components/network/models.py
dockertown/components/node/__init__.py
dockertown/components/node/cli_wrapper.py
dockertown/components/node/models.py
dockertown/components/plugin/__init__.py
dockertown/components/plugin/cli_wrapper.py
dockertown/components/plugin/models.py
dockertown/components/secret/__init__.py
dockertown/components/secret/cli_wrapper.py
dockertown/components/secret/models.py
dockertown/components/service/__init__.py
dockertown/components/service/cli_wrapper.py
dockertown/components/service/models.py
dockertown/components/stack/__init__.py
dockertown-0.2.9.dist-info/licenses/LICENSE
dockertown-0.2.9.dist-info/METADATA
dockertown-0.2.9.dist-info/WHEEL
dockertown-0.2.9.dist-info/entry_points.txt
dockertown-0.2.9.dist-info/top_level.txt
dockertown-0.2.9.dist-info/RECORD
