Metadata-Version: 2.4
Name: dockertown
Version: 0.2.9
Summary: A decent Python wrapper for Docker CLI
License: MIT
Project-URL: Documentation, https://duckietown.github.io/dockertown/
Project-URL: Source Code, https://github.com/duckietown/dockertown
Project-URL: Bug Tracker, https://github.com/duckietown/dockertown/issues
Requires-Python: >=3.7, <4
License-File: LICENSE
Requires-Dist: pydantic>=2.0
Requires-Dist: requests
Requires-Dist: tqdm
Requires-Dist: typer>=0.4.1
Requires-Dist: typing_extensions
Requires-Dist: humanfriendly
Dynamic: description
Dynamic: description-content-type
Dynamic: license
Dynamic: license-file
Dynamic: project-url
Dynamic: requires-dist
Dynamic: requires-python
Dynamic: summary
